langchain_qwq/__init__.py
langchain_qwq/base.py
langchain_qwq/chat_models.py
langchain_qwq/py.typed
langchain_qwq/utils.py
langchain_qwq-0.3.0.dist-info/LICENSE
langchain_qwq-0.3.0.dist-info/METADATA
langchain_qwq-0.3.0.dist-info/WHEEL
langchain_qwq-0.3.0.dist-info/RECORD
