Metadata-Version: 2.1
Name: langchain-qwq
Version: 0.3.0
Summary: An integration package connecting Qwen 3, QwQ and LangChain
Home-page: https://github.com/yigit353/langchain-qwq
License: MIT
Author: Yiğit Bekir Kaya, PhD
Author-email: yigit353@gmail.com
Requires-Python: >=3.10,<4.0
Classifier: License :: OSI Approved :: MIT License
Classifier: Programming Language :: Python :: 3
Classifier: Programming Language :: Python :: 3.10
Classifier: Programming Language :: Python :: 3.11
Classifier: Programming Language :: Python :: 3.12
Provides-Extra: codespell
Provides-Extra: docs
Provides-Extra: lint
Provides-Extra: test
Provides-Extra: typing
Requires-Dist: json-repair (>=0.53.0,<0.54.0)
Requires-Dist: langchain (>=1.0.5,<2.0.0)
Requires-Dist: langchain-openai (>=1.0.2,<2.0.0)
Project-URL: Repository, https://github.com/yigit353/langchain-qwq
Project-URL: Release Notes, https://github.com/langchain-ai/langchain/releases?q=tag%3A%22qwq%3D%3D0%22&expanded=true
Project-URL: Source Code, https://github.com/yigit353/langchain-qwq/tree/main/langchain_qwq
